disco/__init__.py
disco/common.py
disco/enums.py
disco/events.py
disco/exceptions.py
disco/version.py
disco/analysis/__init__.py
disco/analysis/analysis.py
disco/analysis/configure.py
disco/analysis/impact_analysis_inputs.toml
disco/analysis/input.py
disco/analysis/option.py
disco/analysis/postprocess_time_series.py
disco/analysis/snapshot_impact_analysis.py
disco/analysis/time_series_impact_analysis.py
disco/cli/__init__.py
disco/cli/cba_post_process.py
disco/cli/common.py
disco/cli/compute_cba.py
disco/cli/compute_hosting_capacity.py
disco/cli/compute_pv_swad.py
disco/cli/compute_snapshot_hosting_capacity.py
disco/cli/compute_snapshot_impact_analysis.py
disco/cli/compute_time_series_hosting_capacity.py
disco/cli/compute_time_series_impact_analysis.py
disco/cli/config.py
disco/cli/config_generic_models.py
disco/cli/config_snapshot.py
disco/cli/config_time_series.py
disco/cli/config_upgrade.py
disco/cli/configure_analysis.py
disco/cli/create_pipeline.py
disco/cli/disco.py
disco/cli/disco_internal.py
disco/cli/download_source.py
disco/cli/ingest_tables.py
disco/cli/make_cba_tables.py
disco/cli/make_summary_tables.py
disco/cli/make_upgrade_tables.py
disco/cli/plots.py
disco/cli/prescreen_pv_penetration_levels.py
disco/cli/pv_deployments.py
disco/cli/pydss_hosting_capacity.py
disco/cli/simulation_models.py
disco/cli/summarize_hosting_capacity.py
disco/cli/transform_model.py
disco/cli/upgrade_cost_analysis.py
disco/distribution/__init__.py
disco/distribution/deployment_parameters.py
disco/distribution/distribution_configuration.py
disco/distribution/distribution_inputs.py
disco/extensions/__init__.py
disco/extensions/jade_extensions.json
disco/extensions/pydss_simulation/__init__.py
disco/extensions/pydss_simulation/cli.py
disco/extensions/pydss_simulation/estimate_run_minutes.py
disco/extensions/pydss_simulation/pydss_configuration.py
disco/extensions/pydss_simulation/pydss_inputs.py
disco/extensions/pydss_simulation/pydss_simulation.py
NREL_disco-0.5.1.dist-info/LICENSE
NREL_disco-0.5.1.dist-info/METADATA
NREL_disco-0.5.1.dist-info/WHEEL
NREL_disco-0.5.1.dist-info/entry_points.txt
NREL_disco-0.5.1.dist-info/top_level.txt
NREL_disco-0.5.1.dist-info/RECORD
