Metadata-Version: 2.1
Name: NREL-disco
Version: 0.5.1
Summary: DISCO
Home-page: https://github.com/NREL/disco
Maintainer-email: daniel.thom@nrel.gov
License: BSD license
Keywords: disco
Platform: UNKNOWN
Classifier: Development Status :: 4 - Beta
Classifier: License :: OSI Approved :: BSD License
Classifier: Natural Language :: English
Classifier: Programming Language :: Python :: 3.9
Requires-Python: >=3.7
Requires-Dist: NREL-jade ~=0.10.0
Requires-Dist: chevron ~=0.14.0
Requires-Dist: click ~=8.0
Requires-Dist: dsspy ==3.0.2
Requires-Dist: filelock ~=3.8
Requires-Dist: matplotlib ~=3.6
Requires-Dist: networkx ~=2.8
Requires-Dist: opendssdirect.py ~=0.8.4
Requires-Dist: openpyxl ~=3.0
Requires-Dist: pandas <3,>=2
Requires-Dist: pydantic ~=2.5.2
Requires-Dist: seaborn ~=0.12.1
Requires-Dist: scikit-learn <1.4,>=1.1
Requires-Dist: sqlalchemy ~=1.4
Requires-Dist: toml ~=0.10.0
Provides-Extra: dev
Requires-Dist: flake8 ; extra == 'dev'
Requires-Dist: ghp-import ; extra == 'dev'
Requires-Dist: mock >=3.0.0 ; extra == 'dev'
Requires-Dist: pycodestyle ; extra == 'dev'
Requires-Dist: pylint ; extra == 'dev'
Requires-Dist: pytest ; extra == 'dev'
Requires-Dist: pytest-cov ; extra == 'dev'
Requires-Dist: sphinx >=2.0 ; extra == 'dev'
Requires-Dist: sphinx-rtd-theme >=0.4.3 ; extra == 'dev'
Requires-Dist: sphinxcontrib-plantuml ; extra == 'dev'
Requires-Dist: tox ; extra == 'dev'
Provides-Extra: extras
Requires-Dist: ipywidgets ; extra == 'extras'
